ConciseLogging.py
concise_logging-1.0.2.dist-info/METADATA
concise_logging-1.0.2.dist-info/WHEEL
concise_logging-1.0.2.dist-info/top_level.txt
concise_logging-1.0.2.dist-info/RECORD
