Metadata-Version: 2.2
Name: concise-logging
Version: 1.0.2
Summary: An advanced yet easy-to-use logging library.
Author: RuskyDev
Author-email: iamayaanalee@gmail.com
Keywords: logging,advanced logging,easy to use logging,console logging,log levels,custom logger,colorful logging,python logger,python logging,time format logging,unix timestamp logging
Classifier: Programming Language :: Python :: 3
Classifier: License :: OSI Approved :: MIT License
Classifier: Operating System :: OS Independent
Requires-Python: >=3.6
Requires-Dist: colorama
Dynamic: author
Dynamic: author-email
Dynamic: classifier
Dynamic: description
Dynamic: description-content-type
Dynamic: keywords
Dynamic: requires-dist
Dynamic: requires-python
Dynamic: summary
